[{"rec":[{"id":"xb3","name":"SBS-XB3/LC# 蓝色","img":"../images/details/xb3.jpg","price":"RMB 999","checkMore":"details.html"},{"id":"hg1","name":"SBS-HG1/YM# 柠檬黄","img":"../images/details/hg1.jpg","price":"RMB 1,599","checkMore":"details.html"},{"id":"z7","name":"MDR-Z7","img":"../images/details/z7.jpg","price":"RMB 3,699","checkMore":"details.html"},{"id":"z5","name":"XBA-Z5","img":"../images/details/z5.jpg","price":"RMB 3,699","checkMore":"details.html"}]},{"carts":[{"_id":"P98826314","name":"SRS-ZR7/BM黑色","price":"RMB2,099","cartImg":"../images/carts/black.jpg"},{"_id":"P98826315","name":"SRS-ZR7/WM白色","price":"RMB2,099","cartImg":"../images/carts/white.jpg"}]}]